qxenonsign/__init__.py
qxenonsign/core.py
q_xenonsign-1.0.2.dist-info/METADATA
q_xenonsign-1.0.2.dist-info/WHEEL
q_xenonsign-1.0.2.dist-info/top_level.txt
q_xenonsign-1.0.2.dist-info/RECORD
