Metadata-Version: 2.4
Name: Q-XenonSign
Version: 1.0.2
Summary: Q-XenonSign library
Author: Q-XenonSign
Author-email: qxenonsign@gmail.com
Classifier: Programming Language :: Python :: 3
Classifier: License :: OSI Approved :: MIT License
Classifier: Operating System :: OS Independent
Requires-Python: >=3.7
Requires-Dist: numpy
Requires-Dist: requests
Requires-Dist: pydantic
Requires-Dist: pyngrok
Requires-Dist: flask
Dynamic: author
Dynamic: author-email
Dynamic: classifier
Dynamic: description-content-type
Dynamic: requires-dist
Dynamic: requires-python
Dynamic: summary
